slobs_cli-0.11.5.dist-info/METADATA
slobs_cli-0.11.5.dist-info/WHEEL
slobs_cli-0.11.5.dist-info/entry_points.txt
slobs_cli-0.11.5.dist-info/licenses/LICENSE
slobs_cli/__about__.py
slobs_cli/__init__.py
slobs_cli/audio.py
slobs_cli/cli.py
slobs_cli/console.py
slobs_cli/errors.py
slobs_cli/record.py
slobs_cli/replaybuffer.py
slobs_cli/scene.py
slobs_cli/scenecollection.py
slobs_cli/stream.py
slobs_cli/studiomode.py
slobs_cli/styles.py
slobs_cli/util.py
slobs_cli-0.11.5.dist-info/RECORD
