Metadata-Version: 2.1
Name: slobs-cli
Version: 0.11.5
Summary: A command line application for Streamlabs Desktop
Author-Email: onyx-and-iris <code@onyxandiris.online>
License: MIT
Requires-Python: >=3.11
Requires-Dist: pyslobs>=2.0.5
Requires-Dist: asyncclick>=8.1.8
Requires-Dist: rich>=14.0.0
Requires-Dist: anyio>=4.12.0
